README.rst
setup.cfg
setup.py
URF/__init__.py
URF/main.py
URF.egg-info/PKG-INFO
URF.egg-info/SOURCES.txt
URF.egg-info/dependency_links.txt
URF.egg-info/requires.txt
URF.egg-info/top_level.txt