Metadata-Version: 1.1
Name: URF
Version: 0.0.3
Summary: Unsupervised Random Forest (Random Forest Clustering)
Home-page: https://github.com/liyao001/URF
Author: Li Yao
Author-email: yaol17@mails.tsinghua.edu.cn
License: Apache 2.0
Platform: UNKNOWN
Classifier: Intended Audience :: Science/Research
Classifier: Operating System :: OS Independent
Classifier: Programming Language :: Python
Classifier: Topic :: Scientific/Engineering
